[
  {
    "cells": [
      {
        "row_nums": [
          0
        ],
        "column_nums": [
          0,
          1
        ],
        "align": "left",
        "style": "none",
        "indented": false,
        "is_column_header": true,
        "pdf_bbox": [
          56.6849365234375,
          488.2725830078125,
          322.9853210449219,
          497.3187561035156
        ],
        "pdf_text_tight_bbox": [
          56.692901611328125,
          488.2725830078125,
          88.22303009033203,
          497.3187561035156
        ],
        "is_projected_row_header": false,
        "xml_text_content": "Variables",
        "xml_raw_text_content": "Variables",
        "pdf_text_content": "Variables"
      },
      {
        "row_nums": [
          0
        ],
        "column_nums": [
          2,
          3
        ],
        "align": "left",
        "style": "none",
        "indented": false,
        "is_column_header": true,
        "pdf_bbox": [
          359.48077392578125,
          488.2725830078125,
          489.38702392578125,
          497.3187561035156
        ],
        "pdf_text_tight_bbox": [
          359.48876953125,
          488.2725830078125,
          477.4556884765625,
          497.3187561035156
        ],
        "is_projected_row_header": false,
        "xml_text_content": "Household respondents (N = 291)",
        "xml_raw_text_content": "Household respondents (N = 291)",
        "pdf_text_content": "Household respondents (N = 291)"
      },
      {
        "row_nums": [
          1
        ],
        "column_nums": [
          0
        ],
        "align": "unknown",
        "style": "none",
        "indented": false,
        "is_column_header": true,
        "pdf_bbox": [
          56.6849365234375,
          501.4792175292969,
          211.77708435058594,
          510.525390625
        ],
        "pdf_text_tight_bbox": null,
        "is_projected_row_header": false,
        "xml_text_content": "",
        "xml_raw_text_content": "",
        "pdf_text_content": ""
      },
      {
        "row_nums": [
          1
        ],
        "column_nums": [
          1
        ],
        "align": "unknown",
        "style": "none",
        "indented": false,
        "is_column_header": true,
        "pdf_bbox": [
          248.24868774414062,
          501.4792175292969,
          322.9853210449219,
          510.525390625
        ],
        "pdf_text_tight_bbox": null,
        "is_projected_row_header": false,
        "xml_text_content": "",
        "xml_raw_text_content": "",
        "pdf_text_content": ""
      },
      {
        "row_nums": [
          1
        ],
        "column_nums": [
          2
        ],
        "align": "left",
        "style": "none",
        "indented": false,
        "is_column_header": true,
        "pdf_bbox": [
          359.48077392578125,
          501.4792175292969,
          395.4901428222656,
          510.525390625
        ],
        "pdf_text_tight_bbox": [
          359.48876953125,
          501.4792175292969,
          395.4901428222656,
          510.525390625
        ],
        "is_projected_row_header": false,
        "xml_text_content": "Frequency",
        "xml_raw_text_content": "Frequency",
        "pdf_text_content": "Frequency"
      },
      {
        "row_nums": [
          1
        ],
        "column_nums": [
          3
        ],
        "align": "left",
        "style": "none",
        "indented": false,
        "is_column_header": true,
        "pdf_bbox": [
          450.6439208984375,
          501.4792175292969,
          489.38702392578125,
          510.525390625
        ],
        "pdf_text_tight_bbox": [
          450.65191650390625,
          501.4792175292969,
          489.38702392578125,
          510.525390625
        ],
        "is_projected_row_header": false,
        "xml_text_content": "Percentage",
        "xml_raw_text_content": "Percentage",
        "pdf_text_content": "Percentage"
      },
      {
        "row_nums": [
          2,
          3
        ],
        "column_nums": [
          0
        ],
        "align": "left",
        "style": "none",
        "indented": false,
        "is_column_header": false,
        "pdf_bbox": [
          56.6849365234375,
          514.853271484375,
          211.77708435058594,
          535.6953125
        ],
        "pdf_text_tight_bbox": [
          56.692901611328125,
          514.853271484375,
          211.77708435058594,
          523.7320556640625
        ],
        "is_projected_row_header": false,
        "xml_text_content": "Previous malaria history and who got treatment",
        "xml_raw_text_content": "Previous malaria history and who got treatment",
        "pdf_text_content": "Previous malaria history and who got treatment"
      },
      {
        "row_nums": [
          2
        ],
        "column_nums": [
          1
        ],
        "align": "left",
        "style": "none",
        "indented": false,
        "is_column_header": false,
        "pdf_bbox": [
          248.24868774414062,
          514.853271484375,
          322.9853210449219,
          523.7320556640625
        ],
        "pdf_text_tight_bbox": [
          248.25668334960938,
          514.853271484375,
          258.9606628417969,
          523.7320556640625
        ],
        "is_projected_row_header": false,
        "xml_text_content": "Yes",
        "xml_raw_text_content": "Yes",
        "pdf_text_content": "Yes"
      },
      {
        "row_nums": [
          2
        ],
        "column_nums": [
          2
        ],
        "align": "left",
        "style": "none",
        "indented": false,
        "is_column_header": false,
        "pdf_bbox": [
          359.48077392578125,
          514.853271484375,
          395.4901428222656,
          523.7320556640625
        ],
        "pdf_text_tight_bbox": [
          359.4888000488281,
          514.853271484375,
          370.94195556640625,
          523.7320556640625
        ],
        "is_projected_row_header": false,
        "xml_text_content": "244",
        "xml_raw_text_content": "244",
        "pdf_text_content": "244"
      },
      {
        "row_nums": [
          2
        ],
        "column_nums": [
          3
        ],
        "align": "left",
        "style": "none",
        "indented": false,
        "is_column_header": false,
        "pdf_bbox": [
          450.6439208984375,
          514.853271484375,
          489.38702392578125,
          523.7320556640625
        ],
        "pdf_text_tight_bbox": [
          450.65191650390625,
          514.853271484375,
          458.287353515625,
          523.7320556640625
        ],
        "is_projected_row_header": false,
        "xml_text_content": "84",
        "xml_raw_text_content": "84",
        "pdf_text_content": "84"
      },
      {
        "row_nums": [
          3
        ],
        "column_nums": [
          1
        ],
        "align": "left",
        "style": "none",
        "indented": false,
        "is_column_header": false,
        "pdf_bbox": [
          248.24868774414062,
          526.8165283203125,
          322.9853210449219,
          535.6953125
        ],
        "pdf_text_tight_bbox": [
          248.25665283203125,
          526.8165283203125,
          257.5498962402344,
          535.6953125
        ],
        "is_projected_row_header": false,
        "xml_text_content": "No",
        "xml_raw_text_content": "No",
        "pdf_text_content": "No"
      },
      {
        "row_nums": [
          3
        ],
        "column_nums": [
          2
        ],
        "align": "left",
        "style": "none",
        "indented": false,
        "is_column_header": false,
        "pdf_bbox": [
          359.48077392578125,
          526.8165283203125,
          395.4901428222656,
          535.6953125
        ],
        "pdf_text_tight_bbox": [
          359.48876953125,
          526.8165283203125,
          367.12420654296875,
          535.6953125
        ],
        "is_projected_row_header": false,
        "xml_text_content": "47",
        "xml_raw_text_content": "47",
        "pdf_text_content": "47"
      },
      {
        "row_nums": [
          3
        ],
        "column_nums": [
          3
        ],
        "align": "left",
        "style": "none",
        "indented": false,
        "is_column_header": false,
        "pdf_bbox": [
          450.6439208984375,
          526.8165283203125,
          489.38702392578125,
          535.6953125
        ],
        "pdf_text_tight_bbox": [
          450.65191650390625,
          526.8165283203125,
          458.287353515625,
          535.6953125
        ],
        "is_projected_row_header": false,
        "xml_text_content": "16",
        "xml_raw_text_content": "16",
        "pdf_text_content": "16"
      },
      {
        "row_nums": [
          4,
          5,
          6
        ],
        "column_nums": [
          0
        ],
        "align": "left",
        "style": "none",
        "indented": false,
        "is_column_header": false,
        "pdf_bbox": [
          56.6849365234375,
          538.77978515625,
          211.77708435058594,
          571.529296875
        ],
        "pdf_text_tight_bbox": [
          56.692901611328125,
          538.77978515625,
          141.83058166503906,
          547.6585693359375
        ],
        "is_projected_row_header": false,
        "xml_text_content": "Type of malaria drug used",
        "xml_raw_text_content": "Type of malaria drug used",
        "pdf_text_content": "Type of malaria drug used"
      },
      {
        "row_nums": [
          4
        ],
        "column_nums": [
          1
        ],
        "align": "left",
        "style": "none",
        "indented": false,
        "is_column_header": false,
        "pdf_bbox": [
          248.24868774414062,
          538.77978515625,
          322.9853210449219,
          547.6585693359375
        ],
        "pdf_text_tight_bbox": [
          248.2646484375,
          538.77978515625,
          287.5816650390625,
          547.6585693359375
        ],
        "is_projected_row_header": false,
        "xml_text_content": "Chloroquine",
        "xml_raw_text_content": "Chloroquine",
        "pdf_text_content": "Chloroquine"
      },
      {
        "row_nums": [
          4
        ],
        "column_nums": [
          2
        ],
        "align": "left",
        "style": "none",
        "indented": false,
        "is_column_header": false,
        "pdf_bbox": [
          359.48077392578125,
          538.77978515625,
          395.4901428222656,
          547.6585693359375
        ],
        "pdf_text_tight_bbox": [
          359.4967956542969,
          538.77978515625,
          370.949951171875,
          547.6585693359375
        ],
        "is_projected_row_header": false,
        "xml_text_content": "115",
        "xml_raw_text_content": "115",
        "pdf_text_content": "115"
      },
      {
        "row_nums": [
          4
        ],
        "column_nums": [
          3
        ],
        "align": "left",
        "style": "none",
        "indented": false,
        "is_column_header": false,
        "pdf_bbox": [
          450.6439208984375,
          538.77978515625,
          489.38702392578125,
          547.6585693359375
        ],
        "pdf_text_tight_bbox": [
          450.659912109375,
          538.77978515625,
          458.29534912109375,
          547.6585693359375
        ],
        "is_projected_row_header": false,
        "xml_text_content": "47",
        "xml_raw_text_content": "47",
        "pdf_text_content": "47"
      },
      {
        "row_nums": [
          5
        ],
        "column_nums": [
          1
        ],
        "align": "left",
        "style": "none",
        "indented": false,
        "is_column_header": false,
        "pdf_bbox": [
          248.24868774414062,
          550.687255859375,
          322.9853210449219,
          559.5660400390625
        ],
        "pdf_text_tight_bbox": [
          248.25665283203125,
          550.687255859375,
          275.546630859375,
          559.5660400390625
        ],
        "is_projected_row_header": false,
        "xml_text_content": "Coartem",
        "xml_raw_text_content": "Coartem",
        "pdf_text_content": "Coartem"
      },
      {
        "row_nums": [
          5
        ],
        "column_nums": [
          2
        ],
        "align": "left",
        "style": "none",
        "indented": false,
        "is_column_header": false,
        "pdf_bbox": [
          359.48077392578125,
          550.687255859375,
          395.4901428222656,
          559.5660400390625
        ],
        "pdf_text_tight_bbox": [
          359.48876953125,
          550.687255859375,
          367.12420654296875,
          559.5660400390625
        ],
        "is_projected_row_header": false,
        "xml_text_content": "56",
        "xml_raw_text_content": "56",
        "pdf_text_content": "56"
      },
      {
        "row_nums": [
          5
        ],
        "column_nums": [
          3
        ],
        "align": "left",
        "style": "none",
        "indented": false,
        "is_column_header": false,
        "pdf_bbox": [
          450.6439208984375,
          550.687255859375,
          489.38702392578125,
          559.5660400390625
        ],
        "pdf_text_tight_bbox": [
          450.65191650390625,
          550.687255859375,
          458.287353515625,
          559.5660400390625
        ],
        "is_projected_row_header": false,
        "xml_text_content": "23",
        "xml_raw_text_content": "23",
        "pdf_text_content": "23"
      },
      {
        "row_nums": [
          6
        ],
        "column_nums": [
          1
        ],
        "align": "left",
        "style": "none",
        "indented": false,
        "is_column_header": false,
        "pdf_bbox": [
          248.24868774414062,
          562.6505126953125,
          322.9853210449219,
          571.529296875
        ],
        "pdf_text_tight_bbox": [
          248.25665283203125,
          562.6505126953125,
          322.9853210449219,
          571.529296875
        ],
        "is_projected_row_header": false,
        "xml_text_content": "Other antimalarial drug",
        "xml_raw_text_content": "Other antimalarial drug",
        "pdf_text_content": "Other antimalarial drug"
      },
      {
        "row_nums": [
          6
        ],
        "column_nums": [
          2
        ],
        "align": "left",
        "style": "none",
        "indented": false,
        "is_column_header": false,
        "pdf_bbox": [
          359.48077392578125,
          562.6505126953125,
          395.4901428222656,
          571.529296875
        ],
        "pdf_text_tight_bbox": [
          359.48883056640625,
          562.6505126953125,
          367.124267578125,
          571.529296875
        ],
        "is_projected_row_header": false,
        "xml_text_content": "73",
        "xml_raw_text_content": "73",
        "pdf_text_content": "73"
      },
      {
        "row_nums": [
          6
        ],
        "column_nums": [
          3
        ],
        "align": "left",
        "style": "none",
        "indented": false,
        "is_column_header": false,
        "pdf_bbox": [
          450.6439208984375,
          562.6505126953125,
          489.38702392578125,
          571.529296875
        ],
        "pdf_text_tight_bbox": [
          450.6519775390625,
          562.6505126953125,
          458.28741455078125,
          571.529296875
        ],
        "is_projected_row_header": false,
        "xml_text_content": "30",
        "xml_raw_text_content": "30",
        "pdf_text_content": "30"
      },
      {
        "row_nums": [
          7,
          8,
          9
        ],
        "column_nums": [
          0
        ],
        "align": "left",
        "style": "none",
        "indented": false,
        "is_column_header": false,
        "pdf_bbox": [
          56.6849365234375,
          574.61376953125,
          211.77708435058594,
          607.4191284179688
        ],
        "pdf_text_tight_bbox": [
          56.692901611328125,
          574.61376953125,
          115.3216781616211,
          583.4925537109375
        ],
        "is_projected_row_header": false,
        "xml_text_content": "Availability of ITNs",
        "xml_raw_text_content": "Availability of ITNs",
        "pdf_text_content": "Availability of ITNs"
      },
      {
        "row_nums": [
          7
        ],
        "column_nums": [
          1
        ],
        "align": "left",
        "style": "none",
        "indented": false,
        "is_column_header": false,
        "pdf_bbox": [
          248.24868774414062,
          574.61376953125,
          322.9853210449219,
          583.4925537109375
        ],
        "pdf_text_tight_bbox": [
          248.26461791992188,
          574.61376953125,
          274.6220397949219,
          583.4925537109375
        ],
        "is_projected_row_header": false,
        "xml_text_content": "One ITN",
        "xml_raw_text_content": "One ITN",
        "pdf_text_content": "One ITN"
      },
      {
        "row_nums": [
          7
        ],
        "column_nums": [
          2
        ],
        "align": "left",
        "style": "none",
        "indented": false,
        "is_column_header": false,
        "pdf_bbox": [
          359.48077392578125,
          574.61376953125,
          395.4901428222656,
          583.4925537109375
        ],
        "pdf_text_tight_bbox": [
          359.4967041015625,
          574.61376953125,
          367.13214111328125,
          583.4925537109375
        ],
        "is_projected_row_header": false,
        "xml_text_content": "87",
        "xml_raw_text_content": "87",
        "pdf_text_content": "87"
      },
      {
        "row_nums": [
          7
        ],
        "column_nums": [
          3
        ],
        "align": "left",
        "style": "none",
        "indented": false,
        "is_column_header": false,
        "pdf_bbox": [
          450.6439208984375,
          574.61376953125,
          489.38702392578125,
          583.4925537109375
        ],
        "pdf_text_tight_bbox": [
          450.65985107421875,
          574.61376953125,
          463.4360656738281,
          583.4925537109375
        ],
        "is_projected_row_header": false,
        "xml_text_content": "29.9",
        "xml_raw_text_content": "29.9",
        "pdf_text_content": "29.9"
      },
      {
        "row_nums": [
          8
        ],
        "column_nums": [
          1
        ],
        "align": "left",
        "style": "none",
        "indented": false,
        "is_column_header": false,
        "pdf_bbox": [
          248.24868774414062,
          586.5770874023438,
          322.9853210449219,
          595.4558715820312
        ],
        "pdf_text_tight_bbox": [
          248.25665283203125,
          586.5770874023438,
          297.6958312988281,
          595.4558715820312
        ],
        "is_projected_row_header": false,
        "xml_text_content": "More than ITNs",
        "xml_raw_text_content": "More than ITNs",
        "pdf_text_content": "More than ITNs"
      },
      {
        "row_nums": [
          8
        ],
        "column_nums": [
          2
        ],
        "align": "left",
        "style": "none",
        "indented": false,
        "is_column_header": false,
        "pdf_bbox": [
          359.48077392578125,
          586.5770874023438,
          395.4901428222656,
          595.4558715820312
        ],
        "pdf_text_tight_bbox": [
          359.4888000488281,
          586.5770874023438,
          370.94195556640625,
          595.4558715820312
        ],
        "is_projected_row_header": false,
        "xml_text_content": "138",
        "xml_raw_text_content": "138",
        "pdf_text_content": "138"
      },
      {
        "row_nums": [
          8
        ],
        "column_nums": [
          3
        ],
        "align": "left",
        "style": "none",
        "indented": false,
        "is_column_header": false,
        "pdf_bbox": [
          450.6439208984375,
          586.5770874023438,
          489.38702392578125,
          595.4558715820312
        ],
        "pdf_text_tight_bbox": [
          450.65191650390625,
          586.5770874023438,
          463.4281311035156,
          595.4558715820312
        ],
        "is_projected_row_header": false,
        "xml_text_content": "47.8",
        "xml_raw_text_content": "47.8",
        "pdf_text_content": "47.8"
      },
      {
        "row_nums": [
          9
        ],
        "column_nums": [
          1
        ],
        "align": "left",
        "style": "none",
        "indented": false,
        "is_column_header": false,
        "pdf_bbox": [
          248.24868774414062,
          598.5403442382812,
          322.9853210449219,
          607.4191284179688
        ],
        "pdf_text_tight_bbox": [
          248.25665283203125,
          598.5403442382812,
          257.5498962402344,
          607.4191284179688
        ],
        "is_projected_row_header": false,
        "xml_text_content": "No",
        "xml_raw_text_content": "No",
        "pdf_text_content": "No"
      },
      {
        "row_nums": [
          9
        ],
        "column_nums": [
          2
        ],
        "align": "left",
        "style": "none",
        "indented": false,
        "is_column_header": false,
        "pdf_bbox": [
          359.48077392578125,
          598.5403442382812,
          395.4901428222656,
          607.4191284179688
        ],
        "pdf_text_tight_bbox": [
          359.48876953125,
          598.5403442382812,
          367.12420654296875,
          607.4191284179688
        ],
        "is_projected_row_header": false,
        "xml_text_content": "66",
        "xml_raw_text_content": "66",
        "pdf_text_content": "66"
      },
      {
        "row_nums": [
          9
        ],
        "column_nums": [
          3
        ],
        "align": "left",
        "style": "none",
        "indented": false,
        "is_column_header": false,
        "pdf_bbox": [
          450.6439208984375,
          598.5403442382812,
          489.38702392578125,
          607.4191284179688
        ],
        "pdf_text_tight_bbox": [
          450.65191650390625,
          598.5403442382812,
          463.4281311035156,
          607.4191284179688
        ],
        "is_projected_row_header": false,
        "xml_text_content": "22.3",
        "xml_raw_text_content": "22.3",
        "pdf_text_content": "22.3"
      },
      {
        "row_nums": [
          10,
          11
        ],
        "column_nums": [
          0
        ],
        "align": "left",
        "style": "none",
        "indented": false,
        "is_column_header": false,
        "pdf_bbox": [
          56.6849365234375,
          610.5036010742188,
          211.77708435058594,
          631.345703125
        ],
        "pdf_text_tight_bbox": [
          56.692901611328125,
          610.5036010742188,
          144.1020965576172,
          619.3823852539062
        ],
        "is_projected_row_header": false,
        "xml_text_content": "Usage of ITNs in the home",
        "xml_raw_text_content": "Usage of ITNs in the home",
        "pdf_text_content": "Usage of ITNs in the home"
      },
      {
        "row_nums": [
          10
        ],
        "column_nums": [
          1
        ],
        "align": "left",
        "style": "none",
        "indented": false,
        "is_column_header": false,
        "pdf_bbox": [
          248.24868774414062,
          610.5036010742188,
          322.9853210449219,
          619.3823852539062
        ],
        "pdf_text_tight_bbox": [
          248.25668334960938,
          610.5036010742188,
          258.9606628417969,
          619.3823852539062
        ],
        "is_projected_row_header": false,
        "xml_text_content": "Yes",
        "xml_raw_text_content": "Yes",
        "pdf_text_content": "Yes"
      },
      {
        "row_nums": [
          10
        ],
        "column_nums": [
          2
        ],
        "align": "left",
        "style": "none",
        "indented": false,
        "is_column_header": false,
        "pdf_bbox": [
          359.48077392578125,
          610.5036010742188,
          395.4901428222656,
          619.3823852539062
        ],
        "pdf_text_tight_bbox": [
          359.4888000488281,
          610.5036010742188,
          370.94195556640625,
          619.3823852539062
        ],
        "is_projected_row_header": false,
        "xml_text_content": "145",
        "xml_raw_text_content": "145",
        "pdf_text_content": "145"
      },
      {
        "row_nums": [
          10
        ],
        "column_nums": [
          3
        ],
        "align": "left",
        "style": "none",
        "indented": false,
        "is_column_header": false,
        "pdf_bbox": [
          450.6439208984375,
          610.5036010742188,
          489.38702392578125,
          619.3823852539062
        ],
        "pdf_text_tight_bbox": [
          450.65191650390625,
          610.5036010742188,
          463.4281311035156,
          619.3823852539062
        ],
        "is_projected_row_header": false,
        "xml_text_content": "64.4",
        "xml_raw_text_content": "64.4",
        "pdf_text_content": "64.4"
      },
      {
        "row_nums": [
          11
        ],
        "column_nums": [
          1
        ],
        "align": "left",
        "style": "none",
        "indented": false,
        "is_column_header": false,
        "pdf_bbox": [
          248.24868774414062,
          622.4669189453125,
          322.9853210449219,
          631.345703125
        ],
        "pdf_text_tight_bbox": [
          248.25665283203125,
          622.4669189453125,
          257.5498962402344,
          631.345703125
        ],
        "is_projected_row_header": false,
        "xml_text_content": "No",
        "xml_raw_text_content": "No",
        "pdf_text_content": "No"
      },
      {
        "row_nums": [
          11
        ],
        "column_nums": [
          2
        ],
        "align": "left",
        "style": "none",
        "indented": false,
        "is_column_header": false,
        "pdf_bbox": [
          359.48077392578125,
          622.4669189453125,
          395.4901428222656,
          631.345703125
        ],
        "pdf_text_tight_bbox": [
          359.48876953125,
          622.4669189453125,
          367.12420654296875,
          631.345703125
        ],
        "is_projected_row_header": false,
        "xml_text_content": "80",
        "xml_raw_text_content": "80",
        "pdf_text_content": "80"
      },
      {
        "row_nums": [
          11
        ],
        "column_nums": [
          3
        ],
        "align": "left",
        "style": "none",
        "indented": false,
        "is_column_header": false,
        "pdf_bbox": [
          450.6439208984375,
          622.4669189453125,
          489.38702392578125,
          631.345703125
        ],
        "pdf_text_tight_bbox": [
          450.65191650390625,
          622.4669189453125,
          463.4281311035156,
          631.345703125
        ],
        "is_projected_row_header": false,
        "xml_text_content": "35.6",
        "xml_raw_text_content": "35.6",
        "pdf_text_content": "35.6"
      },
      {
        "row_nums": [
          12,
          13
        ],
        "column_nums": [
          0
        ],
        "align": "left",
        "style": "none",
        "indented": false,
        "is_column_header": false,
        "pdf_bbox": [
          56.6849365234375,
          634.43017578125,
          211.77708435058594,
          655.2164306640625
        ],
        "pdf_text_tight_bbox": [
          56.692901611328125,
          634.43017578125,
          156.08131408691406,
          643.3089599609375
        ],
        "is_projected_row_header": false,
        "xml_text_content": "Family members who use ITNs",
        "xml_raw_text_content": "Family members who use ITNs",
        "pdf_text_content": "Family members who use ITNs"
      },
      {
        "row_nums": [
          12
        ],
        "column_nums": [
          1
        ],
        "align": "left",
        "style": "none",
        "indented": false,
        "is_column_header": false,
        "pdf_bbox": [
          248.24868774414062,
          634.43017578125,
          322.9853210449219,
          643.3089599609375
        ],
        "pdf_text_tight_bbox": [
          248.25668334960938,
          634.43017578125,
          290.1799621582031,
          643.3089599609375
        ],
        "is_projected_row_header": false,
        "xml_text_content": "Whole family",
        "xml_raw_text_content": "Whole family",
        "pdf_text_content": "Whole family"
      },
      {
        "row_nums": [
          12
        ],
        "column_nums": [
          2
        ],
        "align": "left",
        "style": "none",
        "indented": false,
        "is_column_header": false,
        "pdf_bbox": [
          359.48077392578125,
          634.43017578125,
          395.4901428222656,
          643.3089599609375
        ],
        "pdf_text_tight_bbox": [
          359.48883056640625,
          634.43017578125,
          367.124267578125,
          643.3089599609375
        ],
        "is_projected_row_header": false,
        "xml_text_content": "11",
        "xml_raw_text_content": "11",
        "pdf_text_content": "11"
      },
      {
        "row_nums": [
          12
        ],
        "column_nums": [
          3
        ],
        "align": "left",
        "style": "none",
        "indented": false,
        "is_column_header": false,
        "pdf_bbox": [
          450.6439208984375,
          634.43017578125,
          489.38702392578125,
          643.3089599609375
        ],
        "pdf_text_tight_bbox": [
          450.6519775390625,
          634.43017578125,
          459.6104736328125,
          643.3089599609375
        ],
        "is_projected_row_header": false,
        "xml_text_content": "7.6",
        "xml_raw_text_content": "7.6",
        "pdf_text_content": "7.6"
      },
      {
        "row_nums": [
          13
        ],
        "column_nums": [
          1
        ],
        "align": "left",
        "style": "none",
        "indented": false,
        "is_column_header": false,
        "pdf_bbox": [
          248.24868774414062,
          646.337646484375,
          322.9853210449219,
          655.2164306640625
        ],
        "pdf_text_tight_bbox": [
          248.25665283203125,
          646.337646484375,
          320.6021423339844,
          655.2164306640625
        ],
        "is_projected_row_header": false,
        "xml_text_content": "Some family members",
        "xml_raw_text_content": "Some family members",
        "pdf_text_content": "Some family members"
      },
      {
        "row_nums": [
          13
        ],
        "column_nums": [
          2
        ],
        "align": "left",
        "style": "none",
        "indented": false,
        "is_column_header": false,
        "pdf_bbox": [
          359.48077392578125,
          646.337646484375,
          395.4901428222656,
          655.2164306640625
        ],
        "pdf_text_tight_bbox": [
          359.48077392578125,
          646.337646484375,
          370.9339294433594,
          655.2164306640625
        ],
        "is_projected_row_header": false,
        "xml_text_content": "134",
        "xml_raw_text_content": "134",
        "pdf_text_content": "134"
      },
      {
        "row_nums": [
          13
        ],
        "column_nums": [
          3
        ],
        "align": "left",
        "style": "none",
        "indented": false,
        "is_column_header": false,
        "pdf_bbox": [
          450.6439208984375,
          646.337646484375,
          489.38702392578125,
          655.2164306640625
        ],
        "pdf_text_tight_bbox": [
          450.6439208984375,
          646.337646484375,
          463.4201354980469,
          655.2164306640625
        ],
        "is_projected_row_header": false,
        "xml_text_content": "92.4",
        "xml_raw_text_content": "92.4",
        "pdf_text_content": "92.4"
      },
      {
        "row_nums": [
          14,
          15
        ],
        "column_nums": [
          0
        ],
        "align": "left",
        "style": "none",
        "indented": false,
        "is_column_header": false,
        "pdf_bbox": [
          56.6849365234375,
          658.3009033203125,
          211.77708435058594,
          679.1429443359375
        ],
        "pdf_text_tight_bbox": [
          56.692901611328125,
          658.3009033203125,
          144.65203857421875,
          667.1796875
        ],
        "is_projected_row_header": false,
        "xml_text_content": "Presence of stagnant water",
        "xml_raw_text_content": "Presence of stagnant water",
        "pdf_text_content": "Presence of stagnant water"
      },
      {
        "row_nums": [
          14
        ],
        "column_nums": [
          1
        ],
        "align": "left",
        "style": "none",
        "indented": false,
        "is_column_header": false,
        "pdf_bbox": [
          248.24868774414062,
          658.3009033203125,
          322.9853210449219,
          667.1796875
        ],
        "pdf_text_tight_bbox": [
          248.25668334960938,
          658.3009033203125,
          258.9606628417969,
          667.1796875
        ],
        "is_projected_row_header": false,
        "xml_text_content": "Yes",
        "xml_raw_text_content": "Yes",
        "pdf_text_content": "Yes"
      },
      {
        "row_nums": [
          14
        ],
        "column_nums": [
          2
        ],
        "align": "left",
        "style": "none",
        "indented": false,
        "is_column_header": false,
        "pdf_bbox": [
          359.48077392578125,
          658.3009033203125,
          395.4901428222656,
          667.1796875
        ],
        "pdf_text_tight_bbox": [
          359.4888000488281,
          658.3009033203125,
          370.94195556640625,
          667.1796875
        ],
        "is_projected_row_header": false,
        "xml_text_content": "167",
        "xml_raw_text_content": "167",
        "pdf_text_content": "167"
      },
      {
        "row_nums": [
          14
        ],
        "column_nums": [
          3
        ],
        "align": "left",
        "style": "none",
        "indented": false,
        "is_column_header": false,
        "pdf_bbox": [
          450.6439208984375,
          658.3009033203125,
          489.38702392578125,
          667.1796875
        ],
        "pdf_text_tight_bbox": [
          450.65191650390625,
          658.3009033203125,
          463.4281311035156,
          667.1796875
        ],
        "is_projected_row_header": false,
        "xml_text_content": "57.4",
        "xml_raw_text_content": "57.4",
        "pdf_text_content": "57.4"
      },
      {
        "row_nums": [
          15
        ],
        "column_nums": [
          1
        ],
        "align": "left",
        "style": "none",
        "indented": false,
        "is_column_header": false,
        "pdf_bbox": [
          248.24868774414062,
          670.26416015625,
          322.9853210449219,
          679.1429443359375
        ],
        "pdf_text_tight_bbox": [
          248.25665283203125,
          670.26416015625,
          257.5498962402344,
          679.1429443359375
        ],
        "is_projected_row_header": false,
        "xml_text_content": "No",
        "xml_raw_text_content": "No",
        "pdf_text_content": "No"
      },
      {
        "row_nums": [
          15
        ],
        "column_nums": [
          2
        ],
        "align": "left",
        "style": "none",
        "indented": false,
        "is_column_header": false,
        "pdf_bbox": [
          359.48077392578125,
          670.26416015625,
          395.4901428222656,
          679.1429443359375
        ],
        "pdf_text_tight_bbox": [
          359.48876953125,
          670.26416015625,
          370.9419250488281,
          679.1429443359375
        ],
        "is_projected_row_header": false,
        "xml_text_content": "124",
        "xml_raw_text_content": "124",
        "pdf_text_content": "124"
      },
      {
        "row_nums": [
          15
        ],
        "column_nums": [
          3
        ],
        "align": "left",
        "style": "none",
        "indented": false,
        "is_column_header": false,
        "pdf_bbox": [
          450.6439208984375,
          670.26416015625,
          489.38702392578125,
          679.1429443359375
        ],
        "pdf_text_tight_bbox": [
          450.65191650390625,
          670.26416015625,
          463.4281311035156,
          679.1429443359375
        ],
        "is_projected_row_header": false,
        "xml_text_content": "42.6",
        "xml_raw_text_content": "42.6",
        "pdf_text_content": "42.6"
      },
      {
        "row_nums": [
          16,
          17
        ],
        "column_nums": [
          0
        ],
        "align": "left",
        "style": "none",
        "indented": false,
        "is_column_header": false,
        "pdf_bbox": [
          56.6849365234375,
          682.2274780273438,
          211.77708435058594,
          703.0695190429688
        ],
        "pdf_text_tight_bbox": [
          56.692901611328125,
          682.2274780273438,
          193.3579559326172,
          691.1062622070312
        ],
        "is_projected_row_header": false,
        "xml_text_content": "Distance stagnant water nearby the home",
        "xml_raw_text_content": "Distance stagnant water nearby the home",
        "pdf_text_content": "Distance stagnant water nearby the home"
      },
      {
        "row_nums": [
          16
        ],
        "column_nums": [
          1
        ],
        "align": "left",
        "style": "none",
        "indented": false,
        "is_column_header": false,
        "pdf_bbox": [
          248.24868774414062,
          682.2274780273438,
          322.9853210449219,
          691.1062622070312
        ],
        "pdf_text_tight_bbox": [
          248.24874877929688,
          682.2274780273438,
          269.2024230957031,
          691.1062622070312
        ],
        "is_projected_row_header": false,
        "xml_text_content": "<1 km",
        "xml_raw_text_content": "<1 km",
        "pdf_text_content": "<1 km"
      },
      {
        "row_nums": [
          16
        ],
        "column_nums": [
          2
        ],
        "align": "left",
        "style": "none",
        "indented": false,
        "is_column_header": false,
        "pdf_bbox": [
          359.48077392578125,
          682.2274780273438,
          395.4901428222656,
          691.1062622070312
        ],
        "pdf_text_tight_bbox": [
          359.48089599609375,
          682.2274780273438,
          367.1163330078125,
          691.1062622070312
        ],
        "is_projected_row_header": false,
        "xml_text_content": "89",
        "xml_raw_text_content": "89",
        "pdf_text_content": "89"
      },
      {
        "row_nums": [
          16
        ],
        "column_nums": [
          3
        ],
        "align": "left",
        "style": "none",
        "indented": false,
        "is_column_header": false,
        "pdf_bbox": [
          450.6439208984375,
          682.2274780273438,
          489.38702392578125,
          691.1062622070312
        ],
        "pdf_text_tight_bbox": [
          450.64404296875,
          682.2274780273438,
          463.4202575683594,
          691.1062622070312
        ],
        "is_projected_row_header": false,
        "xml_text_content": "53.3",
        "xml_raw_text_content": "53.3",
        "pdf_text_content": "53.3"
      },
      {
        "row_nums": [
          17
        ],
        "column_nums": [
          1
        ],
        "align": "left",
        "style": "none",
        "indented": false,
        "is_column_header": false,
        "pdf_bbox": [
          248.24868774414062,
          694.1907348632812,
          322.9853210449219,
          703.0695190429688
        ],
        "pdf_text_tight_bbox": [
          248.25665283203125,
          694.1907348632812,
          269.2103271484375,
          703.0695190429688
        ],
        "is_projected_row_header": false,
        "xml_text_content": "≥1 km",
        "xml_raw_text_content": "≥1 km",
        "pdf_text_content": "≥1 km"
      },
      {
        "row_nums": [
          17
        ],
        "column_nums": [
          2
        ],
        "align": "left",
        "style": "none",
        "indented": false,
        "is_column_header": false,
        "pdf_bbox": [
          359.48077392578125,
          694.1907348632812,
          395.4901428222656,
          703.0695190429688
        ],
        "pdf_text_tight_bbox": [
          359.48876953125,
          694.1907348632812,
          367.12420654296875,
          703.0695190429688
        ],
        "is_projected_row_header": false,
        "xml_text_content": "78",
        "xml_raw_text_content": "78",
        "pdf_text_content": "78"
      },
      {
        "row_nums": [
          17
        ],
        "column_nums": [
          3
        ],
        "align": "left",
        "style": "none",
        "indented": false,
        "is_column_header": false,
        "pdf_bbox": [
          450.6439208984375,
          694.1907348632812,
          489.38702392578125,
          703.0695190429688
        ],
        "pdf_text_tight_bbox": [
          450.65191650390625,
          694.1907348632812,
          463.4281311035156,
          703.0695190429688
        ],
        "is_projected_row_header": false,
        "xml_text_content": "46.7",
        "xml_raw_text_content": "46.7",
        "pdf_text_content": "46.7"
      },
      {
        "row_nums": [
          18,
          19
        ],
        "column_nums": [
          0
        ],
        "align": "left",
        "style": "none",
        "indented": false,
        "is_column_header": false,
        "pdf_bbox": [
          56.6849365234375,
          706.1539916992188,
          211.77708435058594,
          726.99609375
        ],
        "pdf_text_tight_bbox": [
          56.6849365234375,
          706.1539916992188,
          203.6395263671875,
          715.0327758789062
        ],
        "is_projected_row_header": false,
        "xml_text_content": "Chemical spraying habit for mosquito control",
        "xml_raw_text_content": "Chemical spraying habit for mosquito control",
        "pdf_text_content": "Chemical spraying habit for mosquito control"
      },
      {
        "row_nums": [
          18
        ],
        "column_nums": [
          1
        ],
        "align": "left",
        "style": "none",
        "indented": false,
        "is_column_header": false,
        "pdf_bbox": [
          248.24868774414062,
          706.1539916992188,
          322.9853210449219,
          715.0327758789062
        ],
        "pdf_text_tight_bbox": [
          248.2567138671875,
          706.1539916992188,
          258.960693359375,
          715.0327758789062
        ],
        "is_projected_row_header": false,
        "xml_text_content": "Yes",
        "xml_raw_text_content": "Yes",
        "pdf_text_content": "Yes"
      },
      {
        "row_nums": [
          18
        ],
        "column_nums": [
          2
        ],
        "align": "left",
        "style": "none",
        "indented": false,
        "is_column_header": false,
        "pdf_bbox": [
          359.48077392578125,
          706.1539916992188,
          395.4901428222656,
          715.0327758789062
        ],
        "pdf_text_tight_bbox": [
          359.48883056640625,
          706.1539916992188,
          367.124267578125,
          715.0327758789062
        ],
        "is_projected_row_header": false,
        "xml_text_content": "62",
        "xml_raw_text_content": "62",
        "pdf_text_content": "62"
      },
      {
        "row_nums": [
          18
        ],
        "column_nums": [
          3
        ],
        "align": "left",
        "style": "none",
        "indented": false,
        "is_column_header": false,
        "pdf_bbox": [
          450.6439208984375,
          706.1539916992188,
          489.38702392578125,
          715.0327758789062
        ],
        "pdf_text_tight_bbox": [
          450.6519775390625,
          706.1539916992188,
          463.4281921386719,
          715.0327758789062
        ],
        "is_projected_row_header": false,
        "xml_text_content": "21.3",
        "xml_raw_text_content": "21.3",
        "pdf_text_content": "21.3"
      },
      {
        "row_nums": [
          19
        ],
        "column_nums": [
          1
        ],
        "align": "left",
        "style": "none",
        "indented": false,
        "is_column_header": false,
        "pdf_bbox": [
          248.24868774414062,
          718.1173095703125,
          322.9853210449219,
          726.99609375
        ],
        "pdf_text_tight_bbox": [
          248.24868774414062,
          718.1173095703125,
          257.54193115234375,
          726.99609375
        ],
        "is_projected_row_header": false,
        "xml_text_content": "No",
        "xml_raw_text_content": "No",
        "pdf_text_content": "No"
      },
      {
        "row_nums": [
          19
        ],
        "column_nums": [
          2
        ],
        "align": "left",
        "style": "none",
        "indented": false,
        "is_column_header": false,
        "pdf_bbox": [
          359.48077392578125,
          718.1173095703125,
          395.4901428222656,
          726.99609375
        ],
        "pdf_text_tight_bbox": [
          359.4808044433594,
          718.1173095703125,
          370.9339599609375,
          726.99609375
        ],
        "is_projected_row_header": false,
        "xml_text_content": "229",
        "xml_raw_text_content": "229",
        "pdf_text_content": "229"
      },
      {
        "row_nums": [
          19
        ],
        "column_nums": [
          3
        ],
        "align": "left",
        "style": "none",
        "indented": false,
        "is_column_header": false,
        "pdf_bbox": [
          450.6439208984375,
          718.1173095703125,
          489.38702392578125,
          726.99609375
        ],
        "pdf_text_tight_bbox": [
          450.6439208984375,
          718.1173095703125,
          463.4201354980469,
          726.99609375
        ],
        "is_projected_row_header": false,
        "xml_text_content": "78.7",
        "xml_raw_text_content": "78.7",
        "pdf_text_content": "78.7"
      }
    ],
    "rows": [
      {
        "pdf_row_bbox": [
          56.6849365234375,
          488.2725830078125,
          489.38702392578125,
          497.3187561035156
        ],
        "is_column_header": true
      },
      {
        "pdf_row_bbox": [
          56.6849365234375,
          501.4792175292969,
          489.38702392578125,
          510.525390625
        ],
        "is_column_header": true
      },
      {
        "pdf_row_bbox": [
          56.6849365234375,
          514.853271484375,
          489.38702392578125,
          523.7320556640625
        ],
        "is_column_header": false
      },
      {
        "pdf_row_bbox": [
          56.6849365234375,
          526.8165283203125,
          489.38702392578125,
          535.6953125
        ],
        "is_column_header": false
      },
      {
        "pdf_row_bbox": [
          56.6849365234375,
          538.77978515625,
          489.38702392578125,
          547.6585693359375
        ],
        "is_column_header": false
      },
      {
        "pdf_row_bbox": [
          56.6849365234375,
          550.687255859375,
          489.38702392578125,
          559.5660400390625
        ],
        "is_column_header": false
      },
      {
        "pdf_row_bbox": [
          56.6849365234375,
          562.6505126953125,
          489.38702392578125,
          571.529296875
        ],
        "is_column_header": false
      },
      {
        "pdf_row_bbox": [
          56.6849365234375,
          574.61376953125,
          489.38702392578125,
          583.4925537109375
        ],
        "is_column_header": false
      },
      {
        "pdf_row_bbox": [
          56.6849365234375,
          586.5770874023438,
          489.38702392578125,
          595.4558715820312
        ],
        "is_column_header": false
      },
      {
        "pdf_row_bbox": [
          56.6849365234375,
          598.5403442382812,
          489.38702392578125,
          607.4191284179688
        ],
        "is_column_header": false
      },
      {
        "pdf_row_bbox": [
          56.6849365234375,
          610.5036010742188,
          489.38702392578125,
          619.3823852539062
        ],
        "is_column_header": false
      },
      {
        "pdf_row_bbox": [
          56.6849365234375,
          622.4669189453125,
          489.38702392578125,
          631.345703125
        ],
        "is_column_header": false
      },
      {
        "pdf_row_bbox": [
          56.6849365234375,
          634.43017578125,
          489.38702392578125,
          643.3089599609375
        ],
        "is_column_header": false
      },
      {
        "pdf_row_bbox": [
          56.6849365234375,
          646.337646484375,
          489.38702392578125,
          655.2164306640625
        ],
        "is_column_header": false
      },
      {
        "pdf_row_bbox": [
          56.6849365234375,
          658.3009033203125,
          489.38702392578125,
          667.1796875
        ],
        "is_column_header": false
      },
      {
        "pdf_row_bbox": [
          56.6849365234375,
          670.26416015625,
          489.38702392578125,
          679.1429443359375
        ],
        "is_column_header": false
      },
      {
        "pdf_row_bbox": [
          56.6849365234375,
          682.2274780273438,
          489.38702392578125,
          691.1062622070312
        ],
        "is_column_header": false
      },
      {
        "pdf_row_bbox": [
          56.6849365234375,
          694.1907348632812,
          489.38702392578125,
          703.0695190429688
        ],
        "is_column_header": false
      },
      {
        "pdf_row_bbox": [
          56.6849365234375,
          706.1539916992188,
          489.38702392578125,
          715.0327758789062
        ],
        "is_column_header": false
      },
      {
        "pdf_row_bbox": [
          56.6849365234375,
          718.1173095703125,
          489.38702392578125,
          726.99609375
        ],
        "is_column_header": false
      }
    ],
    "columns": [
      {
        "pdf_column_bbox": [
          56.6849365234375,
          488.2725830078125,
          211.77708435058594,
          726.99609375
        ]
      },
      {
        "pdf_column_bbox": [
          248.24868774414062,
          488.2725830078125,
          322.9853210449219,
          726.99609375
        ]
      },
      {
        "pdf_column_bbox": [
          359.48077392578125,
          488.2725830078125,
          395.4901428222656,
          726.99609375
        ]
      },
      {
        "pdf_column_bbox": [
          450.6439208984375,
          488.2725830078125,
          489.38702392578125,
          726.99609375
        ]
      }
    ],
    "pmc_id": "PMC3128012",
    "pdf_file_name": "1475-2875-10-173.pdf",
    "xml_file_name": "1475-2875-10-173.nxml",
    "split": "test",
    "exclude_for_structure": false,
    "exclude_for_detection": true,
    "structure_id": "PMC3128012_table_2",
    "xml_table_index": 2,
    "pdf_page_index": 4,
    "pdf_full_page_bbox": [
      0.0,
      0.0,
      595.2760009765625,
      793.7009887695312
    ],
    "pdf_table_bbox": [
      56.6849365234375,
      488.2725830078125,
      489.38702392578125,
      726.99609375
    ],
    "pdf_table_wrap_bbox": [
      56.6849365234375,
      474.0919494628906,
      489.38702392578125,
      726.99609375
    ],
    "xml_table_wrap_start_character_index": 26603,
    "xml_table_wrap_end_character_index": 29188
  }
]